{
    "status": "0",
    "msg": "",
    "data": {
        "experimentMatched": false,
        "hasUselessMsg": false,
        "batchNo": "0",
        "page": "0",
        "rows": [
            {
                "id": "45730",
                "no": "1661800",
                "nick": "bucinan gamers",
                "avatarUrl": "https://data.lita.cool/user/45730/album/photo_20211206_134618_648_R76698.jpg?t=1638769578648",
                "gender": "2",
                "intro": "Cinta",
                "verifyType": "0",
                "verifyDescrib": "",
                "playerQuality": "1",
                "isActive": false,
                "deleted": false,
                "imUid": "O7M7s8M9QXSuWCk40E0jpg",
                "kolChatStatus": "disabled",
                "isWool": false,
                "hasLwDiscount": false,
                "skillId": "20",
                "skillName": "Teman Curhat",
                "skillBrickIcon": "https://data.lita.cool/static/skill/skill_20_brick.png",
                "skillBrickNewIcon": "https://data.lita.cool/mgr/skill/202311301926/in_chat_brick-icon.png?width=160&height=160",
                "skillBrickMini": "https://data.lita.cool/static/skill/skill_20_brick_mini.png",
                "skillPcIconUrl": "https://data.lita.cool/static/skill/pc/chat_pc_icon.png",
                "skillPcImageUrl": "https://data.lita.cool/mgr/skill/202310081557/in_chat_pc-image.jpeg?width=253&height=320",
                "skillMiniIconUrl": "https://data.lita.cool/static/skill/mini_icon/just_chatting.png",
                "skillLevelId": "0",
                "skillLevelName": "",
                "skillIntro": "Pusing mikirin hidup yang penuh tanda tanya? Sini curhat sama aku kak..di jamin deh bakal plong tu fikira",
                "skillPosition": "",
                "skillAudioUrl": "https://data.lita.cool/user45730/skill/audio_20.mp3?t=1618316456802",
                "skillAudioSeconds": "9",
                "skillPrice": "150.00",
                "skillPriceName": "30menit",
                "skillOrderCount": "8",
                "skillAvgStar": "5.00",
                "skillTags": "",
                "skillType": "2",
                "skillLevelImages": [],
                "onlineInfo": {
                    "userId": "45730",
                    "roomId": "0",
                    "roomName": ""
                },
                "thirdMedias": [],
                "preferredSkills": [],
                "levelAuth": false,
                "guaranteedWin": false,
                "skillTagList": []
            },
            {
                "id": "55158",
                "no": "1312806",
                "nick": "Jennifer's Body",
                "avatarUrl": "https://data.lita.cool/user/55158/album/photo_20210916_020024_039_R51896.png?t=1631728824039",
                "gender": "2",
                "intro": "halo kak aku Jennifer.. aku user mage dan support. aku supel, barbar dan suka bercanda. yuk have fun bareng aku \ud83d\ude18\ud83d\ude18",
                "verifyType": "0",
                "verifyDescrib": "",
                "playerQuality": "1",
                "isActive": false,
                "deleted": false,
                "imUid": "RJfTjl2ESUm7fOPBDM1RLw",
                "kolChatStatus": "disabled",
                "isWool": false,
                "hasLwDiscount": false,
                "skillId": "20",
                "skillName": "Teman Curhat",
                "skillBrickIcon": "https://data.lita.cool/static/skill/skill_20_brick.png",
                "skillBrickNewIcon": "https://data.lita.cool/mgr/skill/202311301926/in_chat_brick-icon.png?width=160&height=160",
                "skillBrickMini": "https://data.lita.cool/static/skill/skill_20_brick_mini.png",
                "skillPcIconUrl": "https://data.lita.cool/static/skill/pc/chat_pc_icon.png",
                "skillPcImageUrl": "https://data.lita.cool/mgr/skill/202310081557/in_chat_pc-image.jpeg?width=253&height=320",
                "skillMiniIconUrl": "https://data.lita.cool/static/skill/mini_icon/just_chatting.png",
                "skillLevelId": "0",
                "skillLevelName": "",
                "skillIntro": "Hai kak aku Jennifer.. Ngobrol ngobrol manja dan seru yuk sama aku. Kenalan boleh kali aja nyaman ya kaaannn \ud83e\udd70\ud83d\ude01",
                "skillPosition": "",
                "skillAudioUrl": "https://data.lita.cool/user55158/skill/audio_20.wav?t=1617791315503",
                "skillAudioSeconds": "12",
                "skillPrice": "150.00",
                "skillPriceName": "30menit",
                "skillOrderCount": "28",
                "skillAvgStar": "4.96",
                "skillTags": "",
                "skillType": "2",
                "skillLevelImages": [],
                "onlineInfo": {
                    "userId": "55158",
                    "roomId": "0",
                    "roomName": ""
                },
                "thirdMedias": [],
                "preferredSkills": [],
                "levelAuth": false,
                "guaranteedWin": false,
                "skillTagList": []
            },
            {
                "id": "69770",
                "no": "1291703",
                "nick": "\ud835\ude7c\ud835\ude74\ud835\ude7b (\u3064\u2267\u25bd\u2266)\u3064",
                "avatarUrl": "https://data.lita.cool/user/69770/album/photo_20210915_224051_149_R40536.png?t=1631716851149",
                "gender": "2",
                "intro": "cuma bisa main game dan tidak memiliki bakat apapun\ud83d\ude07",
                "verifyType": "0",
                "verifyDescrib": "",
                "playerQuality": "1",
                "isActive": false,
                "deleted": false,
                "imUid": "kgUU4481SguqDRPMSPWtNQ",
                "kolChatStatus": "disabled",
                "isWool": false,
                "hasLwDiscount": false,
                "skillId": "20",
                "skillName": "Teman Curhat",
                "skillBrickIcon": "https://data.lita.cool/static/skill/skill_20_brick.png",
                "skillBrickNewIcon": "https://data.lita.cool/mgr/skill/202311301926/in_chat_brick-icon.png?width=160&height=160",
                "skillBrickMini": "https://data.lita.cool/static/skill/skill_20_brick_mini.png",
                "skillPcIconUrl": "https://data.lita.cool/static/skill/pc/chat_pc_icon.png",
                "skillPcImageUrl": "https://data.lita.cool/mgr/skill/202310081557/in_chat_pc-image.jpeg?width=253&height=320",
                "skillMiniIconUrl": "https://data.lita.cool/static/skill/mini_icon/just_chatting.png",
                "skillLevelId": "0",
                "skillLevelName": "",
                "skillIntro": "Haiiiiii aku Melinda\ud83d\ude3c\nKlo kalian butuh tmn curhat / pendengar yg baik aku siap nemenin kalian yuk di order \ud83d\ude09",
                "skillPosition": "",
                "skillAudioUrl": "https://data.lita.cool/user/69770/skill/audio_20_t1638307887107.mp3?t=1638330096396",
                "skillAudioSeconds": "4",
                "skillPrice": "150.00",
                "skillPriceName": "30menit",
                "skillOrderCount": "26",
                "skillAvgStar": "4.92",
                "skillTags": "",
                "skillType": "2",
                "skillLevelImages": [],
                "onlineInfo": {
                    "userId": "69770",
                    "roomId": "0",
                    "roomName": ""
                },
                "thirdMedias": [],
                "preferredSkills": [],
                "levelAuth": false,
                "guaranteedWin": false,
                "skillTagList": []
            },
            {
                "id": "32140",
                "no": "1266179",
                "nick": "Aira Ululu\ud83d\udc51",
                "avatarUrl": "https://data.lita.cool/user/32140/album/photo_20240304_161151_363_R58557.jpg?t=1709539911364",
                "gender": "2",
                "intro": "no love. no problem",
                "verifyType": "0",
                "verifyDescrib": "",
                "playerQuality": "1",
                "isActive": false,
                "deleted": false,
                "imUid": "CfGx0lZERZe6dif8g7r7Vg",
                "kolChatStatus": "disabled",
                "isWool": false,
                "hasLwDiscount": false,
                "skillId": "20",
                "skillName": "Teman Curhat",
                "skillBrickIcon": "https://data.lita.cool/static/skill/skill_20_brick.png",
                "skillBrickNewIcon": "https://data.lita.cool/mgr/skill/202311301926/in_chat_brick-icon.png?width=160&height=160",
                "skillBrickMini": "https://data.lita.cool/static/skill/skill_20_brick_mini.png",
                "skillPcIconUrl": "https://data.lita.cool/static/skill/pc/chat_pc_icon.png",
                "skillPcImageUrl": "https://data.lita.cool/mgr/skill/202310081557/in_chat_pc-image.jpeg?width=253&height=320",
                "skillMiniIconUrl": "https://data.lita.cool/static/skill/mini_icon/just_chatting.png",
                "skillLevelId": "0",
                "skillLevelName": "",
                "skillIntro": "Aku  bisa ngertiin situasi dan kondisi kok\ud83d\ude0a",
                "skillPosition": "",
                "skillAudioUrl": "https://data.lita.cool/user/32140/skill/audio_20_t1670808909474.mp3?t=1670814386330",
                "skillAudioSeconds": "13",
                "skillPrice": "175.00",
                "skillPriceName": "30menit",
                "skillOrderCount": "180",
                "skillAvgStar": "4.97",
                "skillTags": "",
                "skillType": "2",
                "skillLevelImages": [],
                "onlineInfo": {
                    "userId": "32140",
                    "roomId": "0",
                    "roomName": ""
                },
                "thirdMedias": [],
                "preferredSkills": [],
                "levelAuth": false,
                "guaranteedWin": false,
                "skillTagList": []
            },
            {
                "id": "22536",
                "no": "1059975",
                "nick": "Linda\ud83d\udc3e",
                "avatarUrl": "https://data.lita.cool/user/22536/album/photo_20230813_062922_240_R37976.jpg?t=1691879362240",
                "gender": "2",
                "intro": "ayok ka mabar sama aku gif stiker juga boleh",
                "verifyType": "0",
                "verifyDescrib": "",
                "playerQuality": "1",
                "isActive": false,
                "deleted": false,
                "imUid": "ePLz-B7eTXCuC8KXOE-Gkw",
                "kolChatStatus": "disabled",
                "isWool": false,
                "hasLwDiscount": false,
                "skillId": "20",
                "skillName": "Teman Curhat",
                "skillBrickIcon": "https://data.lita.cool/static/skill/skill_20_brick.png",
                "skillBrickNewIcon": "https://data.lita.cool/mgr/skill/202311301926/in_chat_brick-icon.png?width=160&height=160",
                "skillBrickMini": "https://data.lita.cool/static/skill/skill_20_brick_mini.png",
                "skillPcIconUrl": "https://data.lita.cool/static/skill/pc/chat_pc_icon.png",
                "skillPcImageUrl": "https://data.lita.cool/mgr/skill/202310081557/in_chat_pc-image.jpeg?width=253&height=320",
                "skillMiniIconUrl": "https://data.lita.cool/static/skill/mini_icon/just_chatting.png",
                "skillLevelId": "0",
                "skillLevelName": "",
                "skillIntro": "Sini aku temenin ka",
                "skillPosition": "",
                "skillAudioUrl": "https://data.lita.cool/user22536/skill/audio_20.wav?t=1617790579423",
                "skillAudioSeconds": "6",
                "skillPrice": "150.00",
                "skillPriceName": "30Menit",
                "skillOrderCount": "29",
                "skillAvgStar": "5.00",
                "skillTags": "",
                "skillType": "2",
                "skillLevelImages": [],
                "onlineInfo": {
                    "userId": "22536",
                    "roomId": "0",
                    "roomName": ""
                },
                "thirdMedias": [],
                "preferredSkills": [],
                "levelAuth": false,
                "guaranteedWin": false,
                "skillTagList": []
            }
        ]
    }
}